{
  "cause": {
    "item": {
      "item": "additions:tcsponsors-lost_gourd",
      "damage": "any"
    },
    "type": "additions:item_right_click"
  },
  "effects": [
    {
      "type": "additions:consume_item"
    },
    {
      "potion_type": "minecraft:long_leaping",
      "chance": 0.14,
      "type": "additions:potion"
    },
    {
      "potion_type": "minecraft:long_night_vision",
      "chance": 0.14,
      "type": "additions:potion"
    },
    {
      "potion": {
        "name": "minecraft:water_breathing",
        "duration": 1,
        "amplifier": 0,
        "ambient": false,
        "show_particles": true
      },
      "chance": 0.14,
      "type": "additions:potion"
    },
    {
      "potion_type": "minecraft:long_fire_resistance",
      "chance": 0.14,
      "type": "additions:potion"
    },
    {
      "potion": {
        "name": "minecraft:blindness",
        "duration": 400,
        "amplifier": 0,
        "ambient": false,
        "show_particles": true
      },
      "chance": 0.14,
      "type": "additions:potion"
    },
    {
      "potion_type": "minecraft:strong_poison",
      "chance": 0.14,
      "type": "additions:potion"
    },
    {
      "potion_type": "minecraft:long_regeneration",
      "chance": 0.16,
      "type": "additions:potion"
    }
  ]
}